{
  "/my-blog/blog-534": {
    "__comp": "a6aa9e1f",
    "__context": {
      "plugin": "36994c47"
    },
    "sidebar": "814f3328",
    "items": [
      {
        "content": "7661071f"
      },
      {
        "content": "f4f34a3a"
      },
      {
        "content": "8717b14a"
      },
      {
        "content": "925b3f96"
      }
    ],
    "__props": "a2c62bf9"
  },
  "/my-blog/blog/archive-956": {
    "__comp": "9e4087bc",
    "__context": {
      "plugin": "36994c47"
    },
    "__props": "01a328ba"
  },
  "/my-blog/blog/authors-b16": {
    "__comp": "621db11d",
    "__context": {
      "data": {
        "blogMetadata": "acecf23e"
      },
      "plugin": "36994c47"
    },
    "sidebar": "814f3328",
    "__props": "0d7cc0cc"
  },
  "/my-blog/blog/authors/all-sebastien-lorber-articles-159": {
    "__comp": "33fc5bb8",
    "__context": {
      "data": {
        "blogMetadata": "acecf23e"
      },
      "plugin": "36994c47"
    },
    "items": [
      {
        "content": "7661071f"
      },
      {
        "content": "f4f34a3a"
      },
      {
        "content": "925b3f96"
      }
    ],
    "sidebar": "814f3328",
    "__props": "1184d5dc"
  },
  "/my-blog/blog/authors/yangshun-97b": {
    "__comp": "33fc5bb8",
    "__context": {
      "data": {
        "blogMetadata": "acecf23e"
      },
      "plugin": "36994c47"
    },
    "items": [
      {
        "content": "7661071f"
      },
      {
        "content": "8717b14a"
      },
      {
        "content": "925b3f96"
      }
    ],
    "sidebar": "814f3328",
    "__props": "1845bf45"
  },
  "/my-blog/blog/first-blog-post-500": {
    "__comp": "ccc49370",
    "__context": {
      "data": {
        "blogMetadata": "acecf23e"
      },
      "plugin": "36994c47"
    },
    "sidebar": "814f3328",
    "content": "e273c56f"
  },
  "/my-blog/blog/long-blog-post-e71": {
    "__comp": "ccc49370",
    "__context": {
      "data": {
        "blogMetadata": "acecf23e"
      },
      "plugin": "36994c47"
    },
    "sidebar": "814f3328",
    "content": "73664a40"
  },
  "/my-blog/blog/mdx-blog-post-953": {
    "__comp": "ccc49370",
    "__context": {
      "data": {
        "blogMetadata": "acecf23e"
      },
      "plugin": "36994c47"
    },
    "sidebar": "814f3328",
    "content": "59362658"
  },
  "/my-blog/blog/tags-e9a": {
    "__comp": "01a85c17",
    "__context": {
      "plugin": "36994c47"
    },
    "sidebar": "814f3328",
    "__props": "082f35ac"
  },
  "/my-blog/blog/tags/docusaurus-3a4": {
    "__comp": "6875c492",
    "__context": {
      "plugin": "36994c47"
    },
    "sidebar": "814f3328",
    "items": [
      {
        "content": "7661071f"
      },
      {
        "content": "f4f34a3a"
      },
      {
        "content": "8717b14a"
      },
      {
        "content": "925b3f96"
      }
    ],
    "__props": "4d9176cf"
  },
  "/my-blog/blog/tags/facebook-9bb": {
    "__comp": "6875c492",
    "__context": {
      "plugin": "36994c47"
    },
    "sidebar": "814f3328",
    "items": [
      {
        "content": "7661071f"
      }
    ],
    "__props": "6ba7718e"
  },
  "/my-blog/blog/tags/hello-ef2": {
    "__comp": "6875c492",
    "__context": {
      "plugin": "36994c47"
    },
    "sidebar": "814f3328",
    "items": [
      {
        "content": "7661071f"
      },
      {
        "content": "8717b14a"
      }
    ],
    "__props": "0a1ad517"
  },
  "/my-blog/blog/tags/hola-c7f": {
    "__comp": "6875c492",
    "__context": {
      "plugin": "36994c47"
    },
    "sidebar": "814f3328",
    "items": [
      {
        "content": "925b3f96"
      }
    ],
    "__props": "7b021126"
  },
  "/my-blog/blog/welcome-3d6": {
    "__comp": "ccc49370",
    "__context": {
      "data": {
        "blogMetadata": "acecf23e"
      },
      "plugin": "36994c47"
    },
    "sidebar": "814f3328",
    "content": "d9f32620"
  },
  "/my-blog/markdown-page-4dd": {
    "__comp": "1f391b9e",
    "__context": {
      "plugin": "a7456010"
    },
    "content": "393be207"
  },
  "/my-blog/docs-8b4": {
    "__comp": "5e95c892",
    "__context": {
      "plugin": "aba21aa0"
    }
  },
  "/my-blog/docs-76e": {
    "__comp": "a7bd4aaa",
    "__props": "32aee9b9"
  },
  "/my-blog/docs-adc": {
    "__comp": "a94703ab"
  },
  "/my-blog/docs/category/tutorial---basics-40e": {
    "__comp": "14eb3368",
    "__props": "2a07a30a"
  },
  "/my-blog/docs/category/tutorial---extras-39d": {
    "__comp": "14eb3368",
    "__props": "a7b39498"
  },
  "/my-blog/docs/intro-a28": {
    "__comp": "17896441",
    "content": "0e384e19"
  },
  "/my-blog/docs/tutorial-basics/congratulations-529": {
    "__comp": "17896441",
    "content": "822bd8ab"
  },
  "/my-blog/docs/tutorial-basics/create-a-blog-post-dda": {
    "__comp": "17896441",
    "content": "533a09ca"
  },
  "/my-blog/docs/tutorial-basics/create-a-document-7e3": {
    "__comp": "17896441",
    "content": "1e4232ab"
  },
  "/my-blog/docs/tutorial-basics/create-a-page-b5d": {
    "__comp": "17896441",
    "content": "5c868d36"
  },
  "/my-blog/docs/tutorial-basics/deploy-your-site-965": {
    "__comp": "17896441",
    "content": "f55d3e7a"
  },
  "/my-blog/docs/tutorial-basics/markdown-features-a1d": {
    "__comp": "17896441",
    "content": "18c41134"
  },
  "/my-blog/docs/tutorial-extras/manage-docs-versions-212": {
    "__comp": "17896441",
    "content": "dff1c289"
  },
  "/my-blog/docs/tutorial-extras/translate-your-site-f2c": {
    "__comp": "17896441",
    "content": "e44a2883"
  },
  "/my-blog/-4c4": {
    "__comp": "c4f5d8e4",
    "__context": {
      "plugin": "a7456010"
    },
    "config": "5e9f5e1a"
  }
}